dict_deserializer/__init__.py
dict_deserializer/annotations.py
dict_deserializer/deserializer.py
Dictionary_deserializer-0.0.6.dist-info/LICENSE.txt
Dictionary_deserializer-0.0.6.dist-info/METADATA
Dictionary_deserializer-0.0.6.dist-info/WHEEL
Dictionary_deserializer-0.0.6.dist-info/top_level.txt
Dictionary_deserializer-0.0.6.dist-info/RECORD
