Metadata-Version: 2.1
Name: Dictionary-deserializer
Version: 0.0.6
Summary: Dictionary deserializer is a package that aides in the deserializing of JSON (or other structures) that are converted to dicts, into composite classes.
Home-page: https://github.com/rhbvkleef/dict_deserializer
Author: Rolf van Kleef
Author-email: pypi@rolfvankleef.nl
License: UNKNOWN
Platform: UNKNOWN
Classifier: Programming Language :: Python :: 3
Classifier: License :: OSI Approved :: BSD License
Classifier: Operating System :: OS Independent
Classifier: Topic :: Utilities
Classifier: Development Status :: 4 - Beta
Requires-Dist: typeguard
